<?xml version="1.0" encoding="utf-8"?>
<TextureAtlas imagePath="HappyMouseAnimation.png">
	<!-- Created with Adobe Animate version 21.0.7.42652 -->
	<!-- http://www.adobe.com/products/animate.html -->
	<SubTexture name="HappyMouseAnimation0000" x="0" y="0" width="672" height="762" frameX="-121" frameY="-170" frameWidth="822" frameHeight="939"/>
	<SubTexture name="HappyMouseAnimation0001" x="672" y="0" width="706" height="768" frameX="-94" frameY="-170" frameWidth="822" frameHeight="939"/>
	<SubTexture name="HappyMouseAnimation0002" x="1378" y="0" width="704" height="777" frameX="-94" frameY="-161" frameWidth="822" frameHeight="939"/>
	<SubTexture name="HappyMouseAnimation0003" x="2082" y="0" width="727" height="766" frameX="-66" frameY="-173" frameWidth="822" frameHeight="939"/>
	<SubTexture name="HappyMouseAnimation0004" x="2809" y="0" width="719" height="751" frameX="-66" frameY="-188" frameWidth="822" frameHeight="939"/>
	<SubTexture name="HappyMouseAnimation0005" x="3528" y="0" width="720" height="752" frameX="-61" frameY="-165" frameWidth="822" frameHeight="939"/>
	<SubTexture name="HappyMouseAnimation0006" x="4248" y="0" width="705" height="747" frameX="-61" frameY="-170" frameWidth="822" frameHeight="939"/>
	<SubTexture name="HappyMouseAnimation0007" x="4953" y="0" width="705" height="776" frameX="-61" frameY="-151" frameWidth="822" frameHeight="939"/>
	<SubTexture name="HappyMouseAnimation0008" x="5658" y="0" width="692" height="742" frameX="-61" frameY="-185" frameWidth="822" frameHeight="939"/>
	<SubTexture name="HappyMouseAnimation0009" x="6350" y="0" width="687" height="734" frameX="-66" frameY="-188" frameWidth="822" frameHeight="939"/>
	<SubTexture name="HappyMouseAnimation0010" x="7037" y="0" width="687" height="757" frameX="-66" frameY="-165" frameWidth="822" frameHeight="939"/>
	<SubTexture name="HappyMouseAnimation0011" x="0" y="777" width="659" height="745" frameX="-94" frameY="-170" frameWidth="822" frameHeight="939"/>
	<SubTexture name="HappyMouseAnimation0012" x="659" y="777" width="659" height="764" frameX="-94" frameY="-151" frameWidth="822" frameHeight="939"/>
	<SubTexture name="HappyMouseAnimation0013" x="1318" y="777" width="632" height="735" frameX="-121" frameY="-185" frameWidth="822" frameHeight="939"/>
	<SubTexture name="HappyMouseAnimation0014" x="1950" y="777" width="632" height="744" frameX="-121" frameY="-188" frameWidth="822" frameHeight="939"/>
	<SubTexture name="HappyMouseAnimation0015" x="2582" y="777" width="659" height="773" frameX="-94" frameY="-165" frameWidth="822" frameHeight="939"/>
	<SubTexture name="HappyMouseAnimation0016" x="3241" y="777" width="659" height="768" frameX="-94" frameY="-170" frameWidth="822" frameHeight="939"/>
	<SubTexture name="HappyMouseAnimation0017" x="3900" y="777" width="687" height="788" frameX="-66" frameY="-151" frameWidth="822" frameHeight="939"/>
	<SubTexture name="HappyMouseAnimation0018" x="4587" y="777" width="687" height="754" frameX="-66" frameY="-185" frameWidth="822" frameHeight="939"/>
	<SubTexture name="HappyMouseAnimation0019" x="5274" y="777" width="692" height="729" frameX="-61" frameY="-188" frameWidth="822" frameHeight="939"/>
	<SubTexture name="HappyMouseAnimation0020" x="5966" y="777" width="692" height="752" frameX="-61" frameY="-165" frameWidth="822" frameHeight="939"/>
	<SubTexture name="HappyMouseAnimation0021" x="6658" y="777" width="692" height="757" frameX="-61" frameY="-170" frameWidth="822" frameHeight="939"/>
	<SubTexture name="HappyMouseAnimation0022" x="7350" y="777" width="692" height="776" frameX="-61" frameY="-151" frameWidth="822" frameHeight="939"/>
	<SubTexture name="HappyMouseAnimation0023" x="0" y="1565" width="687" height="737" frameX="-66" frameY="-185" frameWidth="822" frameHeight="939"/>
	<SubTexture name="HappyMouseAnimation0024" x="687" y="1565" width="687" height="734" frameX="-66" frameY="-188" frameWidth="822" frameHeight="939"/>
	<SubTexture name="HappyMouseAnimation0025" x="1374" y="1565" width="659" height="750" frameX="-94" frameY="-165" frameWidth="822" frameHeight="939"/>
	<SubTexture name="HappyMouseAnimation0026" x="2033" y="1565" width="659" height="745" frameX="-94" frameY="-170" frameWidth="822" frameHeight="939"/>
	<SubTexture name="HappyMouseAnimation0027" x="2692" y="1565" width="632" height="769" frameX="-121" frameY="-151" frameWidth="822" frameHeight="939"/>
	<SubTexture name="HappyMouseAnimation0028" x="1318" y="777" width="632" height="735" frameX="-121" frameY="-185" frameWidth="822" frameHeight="939"/>
	<SubTexture name="HappyMouseAnimation0029" x="1950" y="777" width="632" height="744" frameX="-121" frameY="-188" frameWidth="822" frameHeight="939"/>
	<SubTexture name="HappyMouseAnimation0030" x="2582" y="777" width="659" height="773" frameX="-94" frameY="-165" frameWidth="822" frameHeight="939"/>
	<SubTexture name="HappyMouseAnimation0031" x="3241" y="777" width="659" height="768" frameX="-94" frameY="-170" frameWidth="822" frameHeight="939"/>
	<SubTexture name="HappyMouseAnimation0032" x="3900" y="777" width="687" height="788" frameX="-66" frameY="-151" frameWidth="822" frameHeight="939"/>
	<SubTexture name="HappyMouseAnimation0033" x="4587" y="777" width="687" height="754" frameX="-66" frameY="-185" frameWidth="822" frameHeight="939"/>
	<SubTexture name="HappyMouseAnimation0034" x="5274" y="777" width="692" height="729" frameX="-61" frameY="-188" frameWidth="822" frameHeight="939"/>
	<SubTexture name="HappyMouseAnimation0035" x="5966" y="777" width="692" height="752" frameX="-61" frameY="-165" frameWidth="822" frameHeight="939"/>
	<SubTexture name="HappyMouseAnimation0036" x="6658" y="777" width="692" height="757" frameX="-61" frameY="-170" frameWidth="822" frameHeight="939"/>
	<SubTexture name="HappyMouseAnimation0037" x="7350" y="777" width="692" height="776" frameX="-61" frameY="-151" frameWidth="822" frameHeight="939"/>
	<SubTexture name="HappyMouseAnimation0038" x="0" y="1565" width="687" height="737" frameX="-66" frameY="-185" frameWidth="822" frameHeight="939"/>
	<SubTexture name="HappyMouseAnimation0039" x="687" y="1565" width="687" height="734" frameX="-66" frameY="-188" frameWidth="822" frameHeight="939"/>
	<SubTexture name="HappyMouseAnimation0040" x="1374" y="1565" width="659" height="750" frameX="-94" frameY="-165" frameWidth="822" frameHeight="939"/>
	<SubTexture name="HappyMouseAnimation0041" x="2033" y="1565" width="659" height="745" frameX="-94" frameY="-170" frameWidth="822" frameHeight="939"/>
	<SubTexture name="HappyMouseAnimation0042" x="2692" y="1565" width="632" height="769" frameX="-121" frameY="-151" frameWidth="822" frameHeight="939"/>
	<SubTexture name="HappyMouseAnimation0043" x="1318" y="777" width="632" height="735" frameX="-121" frameY="-185" frameWidth="822" frameHeight="939"/>
	<SubTexture name="HappyMouseAnimation0044" x="3324" y="1565" width="632" height="776" frameX="-121" frameY="-156" frameWidth="822" frameHeight="939"/>
	<SubTexture name="HappyMouseAnimation0045" x="3956" y="1565" width="659" height="765" frameX="-94" frameY="-173" frameWidth="822" frameHeight="939"/>
	<SubTexture name="HappyMouseAnimation0046" x="4615" y="1565" width="659" height="782" frameX="-94" frameY="-156" frameWidth="822" frameHeight="939"/>
	<SubTexture name="HappyMouseAnimation0047" x="5274" y="1565" width="687" height="771" frameX="-66" frameY="-168" frameWidth="822" frameHeight="939"/>
	<SubTexture name="HappyMouseAnimation0048" x="5961" y="1565" width="687" height="807" frameX="-66" frameY="-132" frameWidth="822" frameHeight="939"/>
	<SubTexture name="HappyMouseAnimation0049" x="6648" y="1565" width="692" height="773" frameX="-61" frameY="-144" frameWidth="822" frameHeight="939"/>
	<SubTexture name="HappyMouseAnimation0050" x="7340" y="1565" width="692" height="787" frameX="-61" frameY="-130" frameWidth="822" frameHeight="939"/>
	<SubTexture name="HappyMouseAnimation0051" x="0" y="2372" width="692" height="764" frameX="-61" frameY="-163" frameWidth="822" frameHeight="939"/>
	<SubTexture name="HappyMouseAnimation0052" x="692" y="2372" width="692" height="795" frameX="-61" frameY="-132" frameWidth="822" frameHeight="939"/>
	<SubTexture name="HappyMouseAnimation0053" x="1384" y="2372" width="687" height="778" frameX="-66" frameY="-144" frameWidth="822" frameHeight="939"/>
	<SubTexture name="HappyMouseAnimation0054" x="2071" y="2372" width="687" height="792" frameX="-66" frameY="-130" frameWidth="822" frameHeight="939"/>
	<SubTexture name="HappyMouseAnimation0055" x="2758" y="2372" width="659" height="752" frameX="-94" frameY="-163" frameWidth="822" frameHeight="939"/>
	<SubTexture name="HappyMouseAnimation0056" x="3417" y="2372" width="659" height="783" frameX="-94" frameY="-132" frameWidth="822" frameHeight="939"/>
	<SubTexture name="HappyMouseAnimation0057" x="4076" y="2372" width="632" height="776" frameX="-121" frameY="-144" frameWidth="822" frameHeight="939"/>
	<SubTexture name="HappyMouseAnimation0058" x="4708" y="2372" width="632" height="790" frameX="-121" frameY="-130" frameWidth="822" frameHeight="939"/>
	<SubTexture name="HappyMouseAnimation0059" x="5340" y="2372" width="632" height="769" frameX="-121" frameY="-163" frameWidth="822" frameHeight="939"/>
	<SubTexture name="HappyMouseAnimation0060" x="5972" y="2372" width="659" height="806" frameX="-94" frameY="-132" frameWidth="822" frameHeight="939"/>
	<SubTexture name="HappyMouseAnimation0061" x="6631" y="2372" width="659" height="794" frameX="-94" frameY="-144" frameWidth="822" frameHeight="939"/>
	<SubTexture name="HappyMouseAnimation0062" x="7290" y="2372" width="687" height="809" frameX="-66" frameY="-130" frameWidth="822" frameHeight="939"/>
	<SubTexture name="HappyMouseAnimation0063" x="0" y="3181" width="687" height="776" frameX="-66" frameY="-163" frameWidth="822" frameHeight="939"/>
	<SubTexture name="HappyMouseAnimation0064" x="687" y="3181" width="692" height="785" frameX="-61" frameY="-132" frameWidth="822" frameHeight="939"/>
	<SubTexture name="HappyMouseAnimation0065" x="1379" y="3181" width="692" height="773" frameX="-61" frameY="-144" frameWidth="822" frameHeight="939"/>
	<SubTexture name="HappyMouseAnimation0066" x="2071" y="3181" width="692" height="797" frameX="-61" frameY="-130" frameWidth="822" frameHeight="939"/>
	<SubTexture name="HappyMouseAnimation0067" x="2763" y="3181" width="692" height="764" frameX="-61" frameY="-163" frameWidth="822" frameHeight="939"/>
	<SubTexture name="HappyMouseAnimation0068" x="3455" y="3181" width="687" height="790" frameX="-66" frameY="-132" frameWidth="822" frameHeight="939"/>
	<SubTexture name="HappyMouseAnimation0069" x="4142" y="3181" width="687" height="778" frameX="-66" frameY="-144" frameWidth="822" frameHeight="939"/>
	<SubTexture name="HappyMouseAnimation0070" x="4829" y="3181" width="659" height="785" frameX="-94" frameY="-130" frameWidth="822" frameHeight="939"/>
	<SubTexture name="HappyMouseAnimation0071" x="5488" y="3181" width="659" height="752" frameX="-94" frameY="-163" frameWidth="822" frameHeight="939"/>
	<SubTexture name="HappyMouseAnimation0072" x="6147" y="3181" width="632" height="788" frameX="-121" frameY="-132" frameWidth="822" frameHeight="939"/>
	<SubTexture name="HappyMouseAnimation0073" x="6779" y="3181" width="632" height="800" frameX="-121" frameY="-132" frameWidth="822" frameHeight="939"/>
	<SubTexture name="HappyMouseAnimation0074" x="7411" y="3181" width="659" height="794" frameX="-94" frameY="-144" frameWidth="822" frameHeight="939"/>
	<SubTexture name="HappyMouseAnimation0075" x="0" y="3981" width="659" height="808" frameX="-94" frameY="-130" frameWidth="822" frameHeight="939"/>
	<SubTexture name="HappyMouseAnimation0076" x="659" y="3981" width="687" height="776" frameX="-66" frameY="-163" frameWidth="822" frameHeight="939"/>
	<SubTexture name="HappyMouseAnimation0077" x="1346" y="3981" width="687" height="807" frameX="-66" frameY="-132" frameWidth="822" frameHeight="939"/>
	<SubTexture name="HappyMouseAnimation0078" x="2033" y="3981" width="692" height="773" frameX="-61" frameY="-144" frameWidth="822" frameHeight="939"/>
	<SubTexture name="HappyMouseAnimation0079" x="2725" y="3981" width="692" height="787" frameX="-61" frameY="-130" frameWidth="822" frameHeight="939"/>
	<SubTexture name="HappyMouseAnimation0080" x="3417" y="3981" width="692" height="764" frameX="-61" frameY="-163" frameWidth="822" frameHeight="939"/>
	<SubTexture name="HappyMouseAnimation0081" x="4109" y="3981" width="692" height="795" frameX="-61" frameY="-132" frameWidth="822" frameHeight="939"/>
	<SubTexture name="HappyMouseAnimation0082" x="4801" y="3981" width="687" height="778" frameX="-66" frameY="-144" frameWidth="822" frameHeight="939"/>
	<SubTexture name="HappyMouseAnimation0083" x="5488" y="3981" width="687" height="792" frameX="-66" frameY="-130" frameWidth="822" frameHeight="939"/>
	<SubTexture name="HappyMouseAnimation0084" x="6175" y="3981" width="659" height="752" frameX="-94" frameY="-163" frameWidth="822" frameHeight="939"/>
	<SubTexture name="HappyMouseAnimation0085" x="6834" y="3981" width="659" height="783" frameX="-94" frameY="-132" frameWidth="822" frameHeight="939"/>
	<SubTexture name="HappyMouseAnimation0086" x="7493" y="3981" width="632" height="776" frameX="-121" frameY="-144" frameWidth="822" frameHeight="939"/>
	<SubTexture name="HappyMouseAnimation0087" x="0" y="4789" width="632" height="876" frameX="-121" frameY="-44" frameWidth="822" frameHeight="939"/>
	<SubTexture name="HappyMouseAnimation0088" x="632" y="4789" width="632" height="864" frameX="-121" frameY="-68" frameWidth="822" frameHeight="939"/>
	<SubTexture name="HappyMouseAnimation0089" x="1264" y="4789" width="659" height="761" frameX="-94" frameY="-177" frameWidth="822" frameHeight="939"/>
	<SubTexture name="HappyMouseAnimation0090" x="1923" y="4789" width="659" height="938" frameX="-94" frameY="0" frameWidth="822" frameHeight="939"/>
	<SubTexture name="HappyMouseAnimation0091" x="2582" y="4789" width="687" height="762" frameX="-66" frameY="-177" frameWidth="822" frameHeight="939"/>
	<SubTexture name="HappyMouseAnimation0092" x="3269" y="4789" width="687" height="850" frameX="-66" frameY="-89" frameWidth="822" frameHeight="939"/>
	<SubTexture name="HappyMouseAnimation0093" x="3956" y="4789" width="692" height="792" frameX="-61" frameY="-125" frameWidth="822" frameHeight="939"/>
	<SubTexture name="HappyMouseAnimation0094" x="4648" y="4789" width="692" height="824" frameX="-61" frameY="-93" frameWidth="822" frameHeight="939"/>
	<SubTexture name="HappyMouseAnimation0095" x="5340" y="4789" width="692" height="810" frameX="-61" frameY="-117" frameWidth="822" frameHeight="939"/>
	<SubTexture name="HappyMouseAnimation0096" x="6032" y="4789" width="692" height="800" frameX="-61" frameY="-127" frameWidth="822" frameHeight="939"/>
	<SubTexture name="HappyMouseAnimation0097" x="6724" y="4789" width="687" height="805" frameX="-66" frameY="-117" frameWidth="822" frameHeight="939"/>
	<SubTexture name="HappyMouseAnimation0098" x="0" y="5727" width="822" height="837" frameX="0" frameY="-91" frameWidth="822" frameHeight="939"/>
</TextureAtlas>
